{
  "run_id": "20260420T101411Z__f25194eb83",
  "analysis_priority": "next_experiment_planning",
  "research_goal": "저전구간에서의 누설전류를 줄여서 터널링 전압 후 전류를 더 증가시키고 싶은데",
  "focus_claims": [],
  "exclude_claims": [],
  "keep_open_claims": [],
  "confirmed_conditions": {},
  "uncertain_conditions": [],
  "assumption_states": {},
  "approved_patch_items": {
    "claims": [],
    "assumptions": [],
    "measurement_conditions": []
  },
  "notes": [
    "저전구간에서의 누설전류를 줄여서 터널링 전압 후 전류를 더 증가시키고 싶은데",
    "저전압구간에 대한 설명을 구체적으로 해줘"
  ],
  "history": [
    {
      "timestamp_utc": "2026-04-20T10:15:09Z",
      "intent_update": {
        "analysis_priority": null,
        "focus_claims": [],
        "exclude_claims": [],
        "keep_open_claims": [],
        "confirmed_conditions": {},
        "uncertain_conditions": [],
        "confirmed_assumptions": [],
        "rejected_assumptions": [],
        "approved_claims": [],
        "approved_assumptions": [],
        "note": null
      },
      "user_text": "저전구간에서의 누설전류를 줄여서 터널링 전압 후 전류를 더 증가시키고 싶은데",
      "structured_answers": []
    },
    {
      "timestamp_utc": "2026-04-20T10:15:30Z",
      "intent_update": {
        "analysis_priority": null,
        "focus_claims": [],
        "exclude_claims": [],
        "keep_open_claims": [],
        "confirmed_conditions": {},
        "uncertain_conditions": [],
        "confirmed_assumptions": [],
        "rejected_assumptions": [],
        "approved_claims": [],
        "approved_assumptions": [],
        "note": null
      },
      "user_text": "저전압구간에 대한 설명을 구체적으로 해줘",
      "structured_answers": []
    }
  ],
  "updated_at_utc": "2026-04-20T10:15:30Z"
}